datadog_checks/dev/__about__.py
datadog_checks/dev/__init__.py
datadog_checks/dev/__main__.py
datadog_checks/dev/_env.py
datadog_checks/dev/ci.py
datadog_checks/dev/conditions.py
datadog_checks/dev/docker.py
datadog_checks/dev/env.py
datadog_checks/dev/errors.py
datadog_checks/dev/fs.py
datadog_checks/dev/http.py
datadog_checks/dev/jmx.py
datadog_checks/dev/kind.py
datadog_checks/dev/kube_port_forward.py
datadog_checks/dev/spec.py
datadog_checks/dev/ssh_tunnel.py
datadog_checks/dev/structures.py
datadog_checks/dev/subprocess.py
datadog_checks/dev/terraform.py
datadog_checks/dev/testing.py
datadog_checks/dev/utils.py
datadog_checks/dev/warn.py
datadog_checks/dev/plugin/__init__.py
datadog_checks/dev/plugin/pytest.py
datadog_checks/dev/tooling/__init__.py
datadog_checks/dev/tooling/__main__.py
datadog_checks/dev/tooling/catalog_const.py
datadog_checks/dev/tooling/clean.py
datadog_checks/dev/tooling/cli.py
datadog_checks/dev/tooling/codeowners.py
datadog_checks/dev/tooling/config.py
datadog_checks/dev/tooling/constants.py
datadog_checks/dev/tooling/create.py
datadog_checks/dev/tooling/datastructures.py
datadog_checks/dev/tooling/dependencies.py
datadog_checks/dev/tooling/git.py
datadog_checks/dev/tooling/github.py
datadog_checks/dev/tooling/license_headers.py
datadog_checks/dev/tooling/manifest_utils.py
datadog_checks/dev/tooling/release.py
datadog_checks/dev/tooling/signing.py
datadog_checks/dev/tooling/testing.py
datadog_checks/dev/tooling/utils.py
datadog_checks/dev/tooling/commands/__init__.py
datadog_checks/dev/tooling/commands/clean.py
datadog_checks/dev/tooling/commands/config.py
datadog_checks/dev/tooling/commands/console.py
datadog_checks/dev/tooling/commands/create.py
datadog_checks/dev/tooling/commands/run.py
datadog_checks/dev/tooling/commands/test.py
datadog_checks/dev/tooling/commands/agent/__init__.py
datadog_checks/dev/tooling/commands/agent/requirements.py
datadog_checks/dev/tooling/commands/ci/__init__.py
datadog_checks_dev-35.5.0.dist-info/METADATA
datadog_checks_dev-35.5.0.dist-info/WHEEL
datadog_checks_dev-35.5.0.dist-info/entry_points.txt
datadog_checks_dev-35.5.0.dist-info/RECORD
