Metadata-Version: 2.4
Name: datadog-checks-dev
Version: 35.5.0
Summary: The Datadog Checks Developer Tool
Project-URL: Source, https://github.com/DataDog/integrations-core
Author-email: Datadog <packages@datadoghq.com>
License-Expression: BSD-3-Clause
Keywords: datadog,datadog agent,datadog check,dev tool,tests
Classifier: Development Status :: 5 - Production/Stable
Classifier: Intended Audience :: Developers
Classifier: Intended Audience :: System Administrators
Classifier: License :: OSI Approved :: BSD License
Classifier: Natural Language :: English
Classifier: Operating System :: OS Independent
Classifier: Programming Language :: Python :: 3.13
Requires-Dist: coverage>=5.0.3
Requires-Dist: flaky>=3.8.0
Requires-Dist: mock
Requires-Dist: pytest-asyncio>=0.23.4
Requires-Dist: pytest-benchmark[histogram]>=4.0.0
Requires-Dist: pytest-cov>=2.6.1
Requires-Dist: pytest-memray>=1.4.0; platform_system == 'Linux' or platform_system == 'Darwin'
Requires-Dist: pytest-mock
Requires-Dist: pytest==8.1.1
Requires-Dist: pyyaml>=5.4.1
Requires-Dist: requests>=2.22.0
Requires-Dist: tenacity
Provides-Extra: cli
Requires-Dist: aiohttp; extra == 'cli'
Requires-Dist: aiomultiprocess; extra == 'cli'
Requires-Dist: atomicwrites; extra == 'cli'
Requires-Dist: beautifulsoup4==4.12.3; extra == 'cli'
Requires-Dist: black==23.12.1; extra == 'cli'
Requires-Dist: build>=0.7.0; extra == 'cli'
Requires-Dist: click~=8.1.6; extra == 'cli'
Requires-Dist: codespell; extra == 'cli'
Requires-Dist: colorama; extra == 'cli'
Requires-Dist: datamodel-code-generator~=0.25.6; extra == 'cli'
Requires-Dist: hatch>=1.5.0; extra == 'cli'
Requires-Dist: in-toto==2.0.0; extra == 'cli'
Requires-Dist: jsonschema; extra == 'cli'
Requires-Dist: markdown; extra == 'cli'
Requires-Dist: orjson; extra == 'cli'
Requires-Dist: packaging; extra == 'cli'
Requires-Dist: pathspec>=0.10.0; extra == 'cli'
Requires-Dist: pip-tools; extra == 'cli'
Requires-Dist: platformdirs>=2.0.0a3; extra == 'cli'
Requires-Dist: pydantic>=2.0.2; extra == 'cli'
Requires-Dist: pysmi==0.3.4; extra == 'cli'
Requires-Dist: securesystemslib[crypto]==0.28.0; extra == 'cli'
Requires-Dist: semver>=2.13.0; extra == 'cli'
Requires-Dist: tabulate>=0.8.9; extra == 'cli'
Requires-Dist: toml<1.0.0,>=0.9.4; extra == 'cli'
Requires-Dist: tomli-w>=1.0.0; extra == 'cli'
Requires-Dist: tomli>=1.1.0; extra == 'cli'
Requires-Dist: towncrier==23.11.0; extra == 'cli'
Requires-Dist: tox<4.0.0,>=3.12.1; extra == 'cli'
Requires-Dist: twine>=1.11.0; extra == 'cli'
Requires-Dist: virtualenv<20.22.0; extra == 'cli'
